supper_regrresion/__init__.py
supper_regrresion/supper_regrression.py
supper_regrresion-1.0.0.dist-info/LICENSE.txt
supper_regrresion-1.0.0.dist-info/METADATA
supper_regrresion-1.0.0.dist-info/WHEEL
supper_regrresion-1.0.0.dist-info/top_level.txt
supper_regrresion-1.0.0.dist-info/RECORD
