Metadata-Version: 2.1
Name: supper-regrresion
Version: 1.0.0
Summary: An awesome package that does something
Home-page: http://pypi.python.org/pypi/supper_regrresion/
Author: Rachid el wa3er
Author-email: rn.benbetka@esi-sba.dz
License: LICENSE.txt
Platform: UNKNOWN
